setup.py
bin/findups
findups/__init__.py
findups/commons.py
findups/scanner.py
findups.egg-info/PKG-INFO
findups.egg-info/SOURCES.txt
findups.egg-info/dependency_links.txt
findups.egg-info/not-zip-safe
findups.egg-info/top_level.txt
findups/comparors/__init__.py
findups/comparors/comparor.py
findups/comparors/dir_entry.py
findups/comparors/mtime.py
findups/comparors/size.py