Metadata-Version: 1.0
Name: findups
Version: 15.4
Summary: Find duplicates across multiple devices.
Home-page: https://github.com/silvavlis/findups
Author: Silvano Cirujano Cuesta
Author-email: silvanociru@gmx.net
License: UNKNOWN
Platform: UNKNOWN
